<?xml version = '1.0' encoding = 'UTF-8'?>
<Relation class="oracle.dbtools.crest.model.design.logical.Relation" name="Rel_1_1_inmueble_tipoestado" directorySegmentName="seg_0" id="7FD963B4-4B0D-8695-5253-9808854FFE92">
<createdBy>jobeso</createdBy>
<createdTime>2024-09-27 21:31:10 UTC</createdTime>
<ownerDesignName>MODELAMIENTO-DATA-INMUEBLES</ownerDesignName>
<engineerTo>
<item key="17CF2EFF-E7A8-FBEC-B05E-8719B0C22D2C" value="true"/>
</engineerTo>
<sourcePk>54A210D9-D849-124B-901D-0973E89B8601</sourcePk>
<targetPk>0D6DD2CA-AB9A-09AA-192A-CAC5EC424EAF</targetPk>
<identifying>false</identifying>
<optionalSource>true</optionalSource>
<optionalTarget>false</optionalTarget>
<sourceCardinality>1</sourceCardinality>
<sourceEntity>5348761B-F9E8-40A0-3968-73EC5DF15050</sourceEntity>
<targetCardinalityString>1</targetCardinalityString>
<targetEntity>7828B73F-7A2A-D3DB-5A4C-C966A6B96340</targetEntity>
<transferable>true</transferable>
<deleteRule>NO ACTION</deleteRule>
</Relation>